pythonHD.py
pythonhd-1.0.0.dist-info/WHEEL
pythonhd-1.0.0.dist-info/METADATA
pythonhd-1.0.0.dist-info/RECORD
